epub_mcp_server/__init__.py
epub_mcp_server/server.py
epub_mcp_server-0.1.1.dist-info/METADATA
epub_mcp_server-0.1.1.dist-info/WHEEL
epub_mcp_server-0.1.1.dist-info/entry_points.txt
epub_mcp_server-0.1.1.dist-info/top_level.txt
epub_mcp_server-0.1.1.dist-info/RECORD
