Metadata-Version: 2.4
Name: epub-mcp-server
Version: 0.1.1
Summary: 智能模板发现助手 - 为 AI 应用提供强大的 epub360 模板搜索能力
Author-email: zhulinyi <536555895@qq.com>
License: MIT
Project-URL: Homepage, https://github.com/21epub/epub-mcp-server
Project-URL: Bug Reports, https://github.com/21epub/epub-mcp-server/issues
Project-URL: Source, https://github.com/21epub/epub-mcp-server
Keywords: mcp,epub360,template,search,ai,assistant
Classifier: Development Status :: 4 - Beta
Classifier: Intended Audience :: Developers
Classifier: License :: OSI Approved :: MIT License
Classifier: Operating System :: OS Independent
Classifier: Programming Language :: Python :: 3
Classifier: Programming Language :: Python :: 3.12
Classifier: Topic :: Software Development :: Libraries :: Python Modules
Classifier: Topic :: Internet :: WWW/HTTP :: HTTP Servers
Classifier: Topic :: Scientific/Engineering :: Artificial Intelligence
Requires-Python: >=3.12
Requires-Dist: mcp==1.9.4
Requires-Dist: requests==2.32.4
